[
    {
        "device_id": "device123",
        "key": "key12345",
        "expirydate": "31-12-2025",
        "Allowoffline": true
    },
    {
        "device_id": "device456",
        "key": "key67890",
        "expirydate": "15-06-2025",
        "Allowoffline": false
    },
    {
        "device_id": "6d8cb0fc5584ccb4",
        "key": "MR",
        "expirydate": "15-06-4000",
        "Allowoffline": false
    },
    {
        "device_id": "e3d8edb9dc5e8383",
        "key": "AMIR",
        "expirydate": "15-06-2026",
        "Allowoffline": false
    },
    {
        "device_id": "e0db484be21722f7",
        "key": "SaJi",
        "expirydate": "15-06-2026",
        "Allowoffline": false
    },
    {
        "device_id": "2af8fcd18916e6d7",
        "key": "OXID",
        "expirydate": "15-06-2026",
        "Allowoffline": false
    },
    {
        "device_id": "0447cc8d07e21e9b",
        "key": "admin",
        "expirydate": "15-10-2025",
        "Allowoffline": false
    },
    {
        "device_id": "f1e10a8c152f84bf",
        "key": "sam",
        "expirydate": "15-10-2024",
        "Allowoffline": false
    },
    {
        "device_id": "228bdc69881ab9e5",
        "key": "silver",
        "expirydate": "15-10-2023",
        "Allowoffline": false
    },
    {
        "device_id": "7f26299a3662fd6a",
        "key": "javad",
        "expirydate": "15-10-2026",
        "Allowoffline": false
    },
    {
        "device_id": "3fb0b8fae377fc44",
        "key": "sajad",
        "expirydate": "15-10-2026",
        "Allowoffline": false
    }
]
